[
  {
    "author_association": "COLLABORATOR",
    "body": "Yeah most of the newer code I see uses `PascalCase` for these. Might be that our naming conventions doc needs an update? /cc @SteveL-MSFT ",
    "created_at": "2020-05-27T19:33:18Z",
    "html_url": "https://github.com/PowerShell/PowerShell/issues/12819#issuecomment-634894420",
    "id": 634894420,
    "issue_url": "https://api.github.com/repos/PowerShell/PowerShell/issues/12819",
    "node_id": "MDEyOklzc3VlQ29tbWVudDYzNDg5NDQyMA==",
    "performed_via_github_app": null,
    "reactions": {
      "+1": 0,
      "-1": 0,
      "confused": 0,
      "eyes": 0,
      "heart": 0,
      "hooray": 0,
      "laugh": 0,
      "rocket": 0,
      "total_count": 0,
      "url": "https://api.github.com/repos/PowerShell/PowerShell/issues/comments/634894420/reactions"
    },
    "updated_at": "2020-05-27T19:33:18Z",
    "url": "https://api.github.com/repos/PowerShell/PowerShell/issues/comments/634894420",
    "user": {
      "avatar_url": "https://avatars.githubusercontent.com/u/32407840?v=4",
      "events_url": "https://api.github.com/users/vexx32/events{/privacy}",
      "followers_url": "https://api.github.com/users/vexx32/followers",
      "following_url": "https://api.github.com/users/vexx32/following{/other_user}",
      "gists_url": "https://api.github.com/users/vexx32/gists{/gist_id}",
      "gravatar_id": "",
      "html_url": "https://github.com/vexx32",
      "id": 32407840,
      "login": "vexx32",
      "node_id": "MDQ6VXNlcjMyNDA3ODQw",
      "organizations_url": "https://api.github.com/users/vexx32/orgs",
      "received_events_url": "https://api.github.com/users/vexx32/received_events",
      "repos_url": "https://api.github.com/users/vexx32/repos",
      "site_admin": false,
      "starred_url": "https://api.github.com/users/vexx32/starred{/owner}{/repo}",
      "subscriptions_url": "https://api.github.com/users/vexx32/subscriptions",
      "type": "User",
      "url": "https://api.github.com/users/vexx32"
    }
  },
  {
    "author_association": "CONTRIBUTOR",
    "body": "https://github.com/dotnet/codeformatter/issues/281#issuecomment-442733951 makes a case that `readonly` should not change the casing style or prefixes.\r\n\r\nI don't have a strong opinion either way, but CodeFactor rules should not conflict with naming conventions – it adds too much friction to pull requests.",
    "created_at": "2020-05-27T19:53:48Z",
    "html_url": "https://github.com/PowerShell/PowerShell/issues/12819#issuecomment-634905416",
    "id": 634905416,
    "issue_url": "https://api.github.com/repos/PowerShell/PowerShell/issues/12819",
    "node_id": "MDEyOklzc3VlQ29tbWVudDYzNDkwNTQxNg==",
    "performed_via_github_app": null,
    "reactions": {
      "+1": 2,
      "-1": 0,
      "confused": 0,
      "eyes": 0,
      "heart": 0,
      "hooray": 0,
      "laugh": 0,
      "rocket": 0,
      "total_count": 2,
      "url": "https://api.github.com/repos/PowerShell/PowerShell/issues/comments/634905416/reactions"
    },
    "updated_at": "2020-05-27T19:53:48Z",
    "url": "https://api.github.com/repos/PowerShell/PowerShell/issues/comments/634905416",
    "user": {
      "avatar_url": "https://avatars.githubusercontent.com/u/45661989?v=4",
      "events_url": "https://api.github.com/users/xtqqczze/events{/privacy}",
      "followers_url": "https://api.github.com/users/xtqqczze/followers",
      "following_url": "https://api.github.com/users/xtqqczze/following{/other_user}",
      "gists_url": "https://api.github.com/users/xtqqczze/gists{/gist_id}",
      "gravatar_id": "",
      "html_url": "https://github.com/xtqqczze",
      "id": 45661989,
      "login": "xtqqczze",
      "node_id": "MDQ6VXNlcjQ1NjYxOTg5",
      "organizations_url": "https://api.github.com/users/xtqqczze/orgs",
      "received_events_url": "https://api.github.com/users/xtqqczze/received_events",
      "repos_url": "https://api.github.com/users/xtqqczze/repos",
      "site_admin": false,
      "starred_url": "https://api.github.com/users/xtqqczze/starred{/owner}{/repo}",
      "subscriptions_url": "https://api.github.com/users/xtqqczze/subscriptions",
      "type": "User",
      "url": "https://api.github.com/users/xtqqczze"
    }
  },
  {
    "author_association": "CONTRIBUTOR",
    "body": "Currently, the PowerShell naming convention states:\r\n> Use `_camelCase` to name internal and private fields and use `readonly` where possible.\r\nPrefix instance fields with `_`, static fields with `s_` and thread static fields with `t_`.\r\n\r\nUnfortunately there is no StyleCop rule available to enforce the use of `_camelCase` for `internal`.\r\n\r\nI think the following changes would be reasonably descriptive of the existing codebase:\r\n* Use `_camelCase` to name private fields (and prefix instance fields with `_`, static fields with `s_` and thread static fields with `t_`).\r\n* Use `PascalCase` to name non-private fields.\r\n\r\nIf we modified the written convention as suggested we could enforce this using the StyleCop rule:\r\n`SA1307: AccessibleFieldsMustBeginWithUpperCaseLetter`.\r\n",
    "created_at": "2020-05-29T23:29:23Z",
    "html_url": "https://github.com/PowerShell/PowerShell/issues/12819#issuecomment-636235142",
    "id": 636235142,
    "issue_url": "https://api.github.com/repos/PowerShell/PowerShell/issues/12819",
    "node_id": "MDEyOklzc3VlQ29tbWVudDYzNjIzNTE0Mg==",
    "performed_via_github_app": null,
    "reactions": {
      "+1": 1,
      "-1": 0,
      "confused": 0,
      "eyes": 0,
      "heart": 0,
      "hooray": 0,
      "laugh": 0,
      "rocket": 0,
      "total_count": 1,
      "url": "https://api.github.com/repos/PowerShell/PowerShell/issues/comments/636235142/reactions"
    },
    "updated_at": "2020-05-29T23:29:23Z",
    "url": "https://api.github.com/repos/PowerShell/PowerShell/issues/comments/636235142",
    "user": {
      "avatar_url": "https://avatars.githubusercontent.com/u/45661989?v=4",
      "events_url": "https://api.github.com/users/xtqqczze/events{/privacy}",
      "followers_url": "https://api.github.com/users/xtqqczze/followers",
      "following_url": "https://api.github.com/users/xtqqczze/following{/other_user}",
      "gists_url": "https://api.github.com/users/xtqqczze/gists{/gist_id}",
      "gravatar_id": "",
      "html_url": "https://github.com/xtqqczze",
      "id": 45661989,
      "login": "xtqqczze",
      "node_id": "MDQ6VXNlcjQ1NjYxOTg5",
      "organizations_url": "https://api.github.com/users/xtqqczze/orgs",
      "received_events_url": "https://api.github.com/users/xtqqczze/received_events",
      "repos_url": "https://api.github.com/users/xtqqczze/repos",
      "site_admin": false,
      "starred_url": "https://api.github.com/users/xtqqczze/starred{/owner}{/repo}",
      "subscriptions_url": "https://api.github.com/users/xtqqczze/subscriptions",
      "type": "User",
      "url": "https://api.github.com/users/xtqqczze"
    }
  },
  {
    "author_association": "CONTRIBUTOR",
    "body": "We should also consider: https://github.com/dotnet/runtime/blob/master/docs/coding-guidelines/coding-style.md\n\n<blockquote><img src=\"https://avatars0.githubusercontent.com/u/9141961?s=400&v=4\" width=\"48\" align=\"right\"><div><img src=\"https://github.githubassets.com/favicons/favicon.svg\" height=\"14\"> GitHub</div><div><strong><a href=\"https://github.com/dotnet/runtime\">dotnet/runtime</a></strong></div><div>.NET is a cross-platform runtime for cloud, mobile, desktop, and IoT apps. - dotnet/runtime</div></blockquote>",
    "created_at": "2020-05-30T00:40:29Z",
    "html_url": "https://github.com/PowerShell/PowerShell/issues/12819#issuecomment-636248328",
    "id": 636248328,
    "issue_url": "https://api.github.com/repos/PowerShell/PowerShell/issues/12819",
    "node_id": "MDEyOklzc3VlQ29tbWVudDYzNjI0ODMyOA==",
    "performed_via_github_app": null,
    "reactions": {
      "+1": 0,
      "-1": 0,
      "confused": 0,
      "eyes": 0,
      "heart": 1,
      "hooray": 0,
      "laugh": 0,
      "rocket": 0,
      "total_count": 1,
      "url": "https://api.github.com/repos/PowerShell/PowerShell/issues/comments/636248328/reactions"
    },
    "updated_at": "2020-05-30T00:40:31Z",
    "url": "https://api.github.com/repos/PowerShell/PowerShell/issues/comments/636248328",
    "user": {
      "avatar_url": "https://avatars.githubusercontent.com/u/45661989?v=4",
      "events_url": "https://api.github.com/users/xtqqczze/events{/privacy}",
      "followers_url": "https://api.github.com/users/xtqqczze/followers",
      "following_url": "https://api.github.com/users/xtqqczze/following{/other_user}",
      "gists_url": "https://api.github.com/users/xtqqczze/gists{/gist_id}",
      "gravatar_id": "",
      "html_url": "https://github.com/xtqqczze",
      "id": 45661989,
      "login": "xtqqczze",
      "node_id": "MDQ6VXNlcjQ1NjYxOTg5",
      "organizations_url": "https://api.github.com/users/xtqqczze/orgs",
      "received_events_url": "https://api.github.com/users/xtqqczze/received_events",
      "repos_url": "https://api.github.com/users/xtqqczze/repos",
      "site_admin": false,
      "starred_url": "https://api.github.com/users/xtqqczze/starred{/owner}{/repo}",
      "subscriptions_url": "https://api.github.com/users/xtqqczze/subscriptions",
      "type": "User",
      "url": "https://api.github.com/users/xtqqczze"
    }
  },
  {
    "author_association": "COLLABORATOR",
    "body": "/cc @adityapatwardhan @daxian-dbw @TravisEz13 Thoughts?",
    "created_at": "2020-05-31T05:09:09Z",
    "html_url": "https://github.com/PowerShell/PowerShell/issues/12819#issuecomment-636422843",
    "id": 636422843,
    "issue_url": "https://api.github.com/repos/PowerShell/PowerShell/issues/12819",
    "node_id": "MDEyOklzc3VlQ29tbWVudDYzNjQyMjg0Mw==",
    "performed_via_github_app": null,
    "reactions": {
      "+1": 0,
      "-1": 0,
      "confused": 0,
      "eyes": 0,
      "heart": 0,
      "hooray": 0,
      "laugh": 0,
      "rocket": 0,
      "total_count": 0,
      "url": "https://api.github.com/repos/PowerShell/PowerShell/issues/comments/636422843/reactions"
    },
    "updated_at": "2020-05-31T05:09:09Z",
    "url": "https://api.github.com/repos/PowerShell/PowerShell/issues/comments/636422843",
    "user": {
      "avatar_url": "https://avatars.githubusercontent.com/u/22290914?v=4",
      "events_url": "https://api.github.com/users/iSazonov/events{/privacy}",
      "followers_url": "https://api.github.com/users/iSazonov/followers",
      "following_url": "https://api.github.com/users/iSazonov/following{/other_user}",
      "gists_url": "https://api.github.com/users/iSazonov/gists{/gist_id}",
      "gravatar_id": "",
      "html_url": "https://github.com/iSazonov",
      "id": 22290914,
      "login": "iSazonov",
      "node_id": "MDQ6VXNlcjIyMjkwOTE0",
      "organizations_url": "https://api.github.com/users/iSazonov/orgs",
      "received_events_url": "https://api.github.com/users/iSazonov/received_events",
      "repos_url": "https://api.github.com/users/iSazonov/repos",
      "site_admin": false,
      "starred_url": "https://api.github.com/users/iSazonov/starred{/owner}{/repo}",
      "subscriptions_url": "https://api.github.com/users/iSazonov/subscriptions",
      "type": "User",
      "url": "https://api.github.com/users/iSazonov"
    }
  },
  {
    "author_association": "MEMBER",
    "body": "If we want to modify our code style, we should modify our code style doc.  We can discuss it there.  I would suggest one issue at a time and not changing any existing rule without a good reason.  the main reason for them is internal consistency.   cc @daxian-dbw ",
    "created_at": "2020-06-02T18:51:37Z",
    "html_url": "https://github.com/PowerShell/PowerShell/issues/12819#issuecomment-637740931",
    "id": 637740931,
    "issue_url": "https://api.github.com/repos/PowerShell/PowerShell/issues/12819",
    "node_id": "MDEyOklzc3VlQ29tbWVudDYzNzc0MDkzMQ==",
    "performed_via_github_app": null,
    "reactions": {
      "+1": 0,
      "-1": 0,
      "confused": 0,
      "eyes": 0,
      "heart": 0,
      "hooray": 0,
      "laugh": 0,
      "rocket": 0,
      "total_count": 0,
      "url": "https://api.github.com/repos/PowerShell/PowerShell/issues/comments/637740931/reactions"
    },
    "updated_at": "2020-06-02T18:52:39Z",
    "url": "https://api.github.com/repos/PowerShell/PowerShell/issues/comments/637740931",
    "user": {
      "avatar_url": "https://avatars.githubusercontent.com/u/10873629?v=4",
      "events_url": "https://api.github.com/users/TravisEz13/events{/privacy}",
      "followers_url": "https://api.github.com/users/TravisEz13/followers",
      "following_url": "https://api.github.com/users/TravisEz13/following{/other_user}",
      "gists_url": "https://api.github.com/users/TravisEz13/gists{/gist_id}",
      "gravatar_id": "",
      "html_url": "https://github.com/TravisEz13",
      "id": 10873629,
      "login": "TravisEz13",
      "node_id": "MDQ6VXNlcjEwODczNjI5",
      "organizations_url": "https://api.github.com/users/TravisEz13/orgs",
      "received_events_url": "https://api.github.com/users/TravisEz13/received_events",
      "repos_url": "https://api.github.com/users/TravisEz13/repos",
      "site_admin": false,
      "starred_url": "https://api.github.com/users/TravisEz13/starred{/owner}{/repo}",
      "subscriptions_url": "https://api.github.com/users/TravisEz13/subscriptions",
      "type": "User",
      "url": "https://api.github.com/users/TravisEz13"
    }
  }
]
