[
  {
    "author_association": "MEMBER",
    "body": "PowerShell regex processing simply depends on dotnet regex processing.  If you have any specific requests, you should probably open it on their repo https://github.com/dotnet/corefx and we would get it \"for free\"",
    "created_at": "2017-06-20T20:07:28Z",
    "html_url": "https://github.com/PowerShell/PowerShell/issues/4057#issuecomment-309876172",
    "id": 309876172,
    "issue_url": "https://api.github.com/repos/PowerShell/PowerShell/issues/4057",
    "node_id": "MDEyOklzc3VlQ29tbWVudDMwOTg3NjE3Mg==",
    "performed_via_github_app": null,
    "reactions": {
      "+1": 0,
      "-1": 0,
      "confused": 0,
      "eyes": 0,
      "heart": 0,
      "hooray": 0,
      "laugh": 0,
      "rocket": 0,
      "total_count": 0,
      "url": "https://api.github.com/repos/PowerShell/PowerShell/issues/comments/309876172/reactions"
    },
    "updated_at": "2017-06-20T20:07:28Z",
    "url": "https://api.github.com/repos/PowerShell/PowerShell/issues/comments/309876172",
    "user": {
      "avatar_url": "https://avatars.githubusercontent.com/u/11859881?v=4",
      "events_url": "https://api.github.com/users/SteveL-MSFT/events{/privacy}",
      "followers_url": "https://api.github.com/users/SteveL-MSFT/followers",
      "following_url": "https://api.github.com/users/SteveL-MSFT/following{/other_user}",
      "gists_url": "https://api.github.com/users/SteveL-MSFT/gists{/gist_id}",
      "gravatar_id": "",
      "html_url": "https://github.com/SteveL-MSFT",
      "id": 11859881,
      "login": "SteveL-MSFT",
      "node_id": "MDQ6VXNlcjExODU5ODgx",
      "organizations_url": "https://api.github.com/users/SteveL-MSFT/orgs",
      "received_events_url": "https://api.github.com/users/SteveL-MSFT/received_events",
      "repos_url": "https://api.github.com/users/SteveL-MSFT/repos",
      "site_admin": false,
      "starred_url": "https://api.github.com/users/SteveL-MSFT/starred{/owner}{/repo}",
      "subscriptions_url": "https://api.github.com/users/SteveL-MSFT/subscriptions",
      "type": "User",
      "url": "https://api.github.com/users/SteveL-MSFT"
    }
  },
  {
    "author_association": "NONE",
    "body": "Thanks, Steve. Will do.",
    "created_at": "2017-06-21T02:39:46Z",
    "html_url": "https://github.com/PowerShell/PowerShell/issues/4057#issuecomment-309946482",
    "id": 309946482,
    "issue_url": "https://api.github.com/repos/PowerShell/PowerShell/issues/4057",
    "node_id": "MDEyOklzc3VlQ29tbWVudDMwOTk0NjQ4Mg==",
    "performed_via_github_app": null,
    "reactions": {
      "+1": 0,
      "-1": 0,
      "confused": 0,
      "eyes": 0,
      "heart": 0,
      "hooray": 0,
      "laugh": 0,
      "rocket": 0,
      "total_count": 0,
      "url": "https://api.github.com/repos/PowerShell/PowerShell/issues/comments/309946482/reactions"
    },
    "updated_at": "2017-06-21T02:39:46Z",
    "url": "https://api.github.com/repos/PowerShell/PowerShell/issues/comments/309946482",
    "user": {
      "avatar_url": "https://avatars.githubusercontent.com/u/2530958?v=4",
      "events_url": "https://api.github.com/users/Liturgist/events{/privacy}",
      "followers_url": "https://api.github.com/users/Liturgist/followers",
      "following_url": "https://api.github.com/users/Liturgist/following{/other_user}",
      "gists_url": "https://api.github.com/users/Liturgist/gists{/gist_id}",
      "gravatar_id": "",
      "html_url": "https://github.com/Liturgist",
      "id": 2530958,
      "login": "Liturgist",
      "node_id": "MDQ6VXNlcjI1MzA5NTg=",
      "organizations_url": "https://api.github.com/users/Liturgist/orgs",
      "received_events_url": "https://api.github.com/users/Liturgist/received_events",
      "repos_url": "https://api.github.com/users/Liturgist/repos",
      "site_admin": false,
      "starred_url": "https://api.github.com/users/Liturgist/starred{/owner}{/repo}",
      "subscriptions_url": "https://api.github.com/users/Liturgist/subscriptions",
      "type": "User",
      "url": "https://api.github.com/users/Liturgist"
    }
  }
]
