{
  "_url": "https://github.com/PowerShell/PowerShell/issues/3947",
  "author": "daxian-dbw",
  "body": "- [x] Need to update the first section about building candidate packages as we are switching to VSTS.\r\n- [x] Need to capture the details about how to trigger the windows docker build.",
  "closed_at": "2017-06-07T00:30:52Z",
  "comments": [
    {
      "author": "daxian-dbw",
      "author_association": "MEMBER",
      "body": "Fixed via https://github.com/PowerShell/Internal-PowerShellTeam-Tools/pull/238",
      "created_at": "2017-06-07T00:30:52Z",
      "updated_at": "2017-06-07T00:30:52Z"
    }
  ],
  "created_at": "2017-06-06T04:59:26Z",
  "number": 3947,
  "state": "closed",
  "title": "Need to update Internal-PowerShellTeam-Tools/StepsToReleasePSCore.md",
  "updated_at": "2017-06-11T10:13:29Z"
}