{
  "_url": "https://github.com/PowerShell/PowerShell/issues/742",
  "author": "zach-folwick",
  "body": "Added MMI.Native code.  This allows users to create a ciminstance and properties using the Microsoft.Management.Infrastructure library.\n\n<!-- Reviewable:start -->\n\n---\n\nThis change is [<img src=\"https://reviewable.io/review_button.svg\" height=\"35\" align=\"absmiddle\" alt=\"Reviewable\"/>](https://reviewable.io/reviews/powershell/powershell/742)\n\n<!-- Reviewable:end -->\n",
  "closed_at": "2016-04-14T18:51:27Z",
  "comments": [
    {
      "author": "zach-folwick",
      "author_association": "CONTRIBUTOR",
      "body": "blocked by #454.\n\nWe require OMI to access the MI library.\n",
      "created_at": "2016-03-30T23:05:12Z",
      "updated_at": "2016-03-30T23:05:12Z"
    },
    {
      "author": "andschwa",
      "author_association": "MEMBER",
      "body": "I thought you were working around this by committing the libraries directly.\n",
      "created_at": "2016-03-30T23:08:00Z",
      "updated_at": "2016-03-30T23:08:00Z"
    },
    {
      "author": "zach-folwick",
      "author_association": "CONTRIBUTOR",
      "body": "I was hoping to have done that with just copying libmi.so, but it relies on other things.  The other alternative (copying all of omi, or going through and figuring out each file needed by mi.h) is sub-optimal.  I think using a workaround would be just creating more work for someone else later, and doing it \"right\" the first time is the cheapest and best option.\n",
      "created_at": "2016-03-30T23:12:48Z",
      "updated_at": "2016-03-30T23:12:48Z"
    },
    {
      "author": "andschwa",
      "author_association": "MEMBER",
      "body": "All right I've added the PowerShell CI user as an external collaborator with read-only access to OMI. Please try again.\n",
      "created_at": "2016-03-30T23:16:30Z",
      "updated_at": "2016-03-30T23:16:30Z"
    },
    {
      "author": "andschwa",
      "author_association": "MEMBER",
      "body": "@paulcallen Going to close this since it won't be merged; it'll stick around though for the changes.\n",
      "created_at": "2016-04-14T18:51:27Z",
      "updated_at": "2016-04-14T18:51:27Z"
    }
  ],
  "created_at": "2016-03-25T20:58:16Z",
  "number": 742,
  "state": "closed",
  "title": "Ciminstance",
  "updated_at": "2016-04-14T18:51:31Z"
}